simtypes/__init__.py
simtypes/check.py
simtypes/from_string.py
simtypes/py.typed
simtypes/typing.py
simtypes/types/__init__.py
simtypes/types/ints/__init__.py
simtypes/types/ints/natural.py
simtypes/types/ints/non_negative.py
simtypes/types/strings/email.py
simtypes-0.0.10.dist-info/LICENSE
simtypes-0.0.10.dist-info/METADATA
simtypes-0.0.10.dist-info/WHEEL
simtypes-0.0.10.dist-info/top_level.txt
simtypes-0.0.10.dist-info/RECORD
